lighter/__init__.py
lighter/constants.py
lighter/errors.py
lighter/lighter_client.py
lighter/abi/erc20.json
lighter/abi/factory.json
lighter/abi/orderbook.json
lighter/abi/router.json
lighter/helpers/__init__.py
lighter/helpers/request_helpers.py
lighter/helpers/requests.py
lighter/modules/__init__.py
lighter/modules/api.py
lighter/modules/blockchain.py
lighter/tests/__init__.py
lighter/tests/test_blockchain.py
lighter_python_v1-1.0.0.dist-info/LICENSE
lighter_python_v1-1.0.0.dist-info/METADATA
lighter_python_v1-1.0.0.dist-info/WHEEL
lighter_python_v1-1.0.0.dist-info/top_level.txt
lighter_python_v1-1.0.0.dist-info/RECORD
